{
	"format_version": "1.8.0",
	"animations": {
		"eat": {
			"loop": true,
			"animation_length": 3.0833,
			"bones": {
				"Body": {
					"rotation": {
						"0.0": {
							"post": {
								"vector": [0, 0, 0]
							},
							"lerp_mode": "catmullrom"
						},
						"0.375": {
							"post": {
								"vector": [20, 0, 0]
							},
							"lerp_mode": "catmullrom"
						},
						"2.25": {
							"post": {
								"vector": [20, 0, 0]
							},
							"lerp_mode": "catmullrom"
						},
						"2.625": {
							"post": {
								"vector": [0, 0, 0]
							},
							"lerp_mode": "catmullrom"
						}
					},
					"position": {
						"0.0": {
							"post": {
								"vector": [0, 0, 0]
							},
							"lerp_mode": "catmullrom"
						},
						"0.375": {
							"post": {
								"vector": [0, 0, 0]
							},
							"lerp_mode": "catmullrom"
						},
						"2.25": {
							"post": {
								"vector": [0, 0, 0]
							},
							"lerp_mode": "catmullrom"
						},
						"2.625": {
							"post": {
								"vector": [0, 0, 0]
							},
							"lerp_mode": "catmullrom"
						}
					}
				},
				"Tail": {
					"rotation": {
						"0.0": {
							"vector": [0, 0, 0]
						},
						"0.3333": {
							"pre": {
								"vector": [17.5, 0, 0]
							},
							"post": {
								"vector": [17.5, 0, 0]
							},
							"lerp_mode": "catmullrom"
						},
						"0.9167": {
							"post": {
								"vector": [-27.5, 0, 0]
							},
							"lerp_mode": "catmullrom"
						},
						"2.5417": {
							"post": {
								"vector": [-27.5, 0, 0]
							},
							"lerp_mode": "catmullrom"
						},
						"2.8333": {
							"vector": [0, 0, 0]
						}
					},
					"position": {
						"0.0": {
							"vector": [0, 0, 0]
						},
						"2.8333": {
							"vector": [0, 0, 0]
						}
					}
				},
				"neck": {
					"rotation": {
						"0.0": {
							"post": {
								"vector": [0, 0, 0]
							},
							"lerp_mode": "catmullrom"
						},
						"0.2083": {
							"post": {
								"vector": [-7.5, 0, 0]
							},
							"lerp_mode": "catmullrom"
						},
						"0.5": {
							"post": {
								"vector": [55, 0, 0]
							},
							"lerp_mode": "catmullrom"
						},
						"0.75": {
							"post": {
								"vector": [50, 0, 0]
							},
							"lerp_mode": "catmullrom"
						},
						"1.0": {
							"post": {
								"vector": [55, 0, 0]
							},
							"lerp_mode": "catmullrom"
						},
						"1.25": {
							"post": {
								"vector": [50, 0, 0]
							},
							"lerp_mode": "catmullrom"
						},
						"1.5": {
							"post": {
								"vector": [55, 0, 0]
							},
							"lerp_mode": "catmullrom"
						},
						"1.75": {
							"post": {
								"vector": [50, 0, 0]
							},
							"lerp_mode": "catmullrom"
						},
						"2.0": {
							"post": {
								"vector": [55, 0, 0]
							},
							"lerp_mode": "catmullrom"
						},
						"2.25": {
							"post": {
								"vector": [50, 0, 0]
							},
							"lerp_mode": "catmullrom"
						},
						"2.75": {
							"post": {
								"vector": [0, 0, 0]
							},
							"lerp_mode": "catmullrom"
						}
					},
					"position": {
						"0.0": {
							"post": {
								"vector": [0, 0, 0]
							},
							"lerp_mode": "catmullrom"
						},
						"2.75": {
							"post": {
								"vector": [0, 0, 0]
							},
							"lerp_mode": "catmullrom"
						}
					}
				},
				"head": {
					"rotation": {
						"0.0": {
							"vector": [0, 0, 0]
						},
						"0.625": {
							"vector": [0, 0, 0]
						},
						"0.875": {
							"pre": {
								"vector": [-7.5, 0, 0]
							},
							"post": {
								"vector": [-7.5, 0, 0]
							},
							"lerp_mode": "catmullrom"
						},
						"1.125": {
							"post": {
								"vector": [0, 0, 0]
							},
							"lerp_mode": "catmullrom"
						},
						"1.375": {
							"post": {
								"vector": [-7.5, 0, 0]
							},
							"lerp_mode": "catmullrom"
						},
						"1.625": {
							"post": {
								"vector": [0, 0, 0]
							},
							"lerp_mode": "catmullrom"
						},
						"1.875": {
							"post": {
								"vector": [-7.5, 0, 0]
							},
							"lerp_mode": "catmullrom"
						},
						"2.125": {
							"post": {
								"vector": [0, 0, 0]
							},
							"lerp_mode": "catmullrom"
						},
						"2.5": {
							"post": {
								"vector": [7.5, 0, 0]
							},
							"lerp_mode": "catmullrom"
						},
						"2.8333": {
							"vector": [0, 0, 0]
						}
					},
					"position": {
						"0.0": {
							"vector": [0, 0, 0]
						},
						"0.5": {
							"vector": [0, 0, 0]
						},
						"2.8333": {
							"vector": [0, 0, 0]
						}
					}
				},
				"jaw": {
					"rotation": {
						"0.0": {
							"vector": [0, 0, 0]
						},
						"0.2083": {
							"vector": [0, 0, 0]
						},
						"0.5": {
							"pre": {
								"vector": [15, 0, 0]
							},
							"post": {
								"vector": [15, 0, 0]
							},
							"lerp_mode": "catmullrom"
						},
						"0.75": {
							"post": {
								"vector": [0, 0, 0]
							},
							"lerp_mode": "catmullrom"
						},
						"1.0": {
							"post": {
								"vector": [15, 0, 0]
							},
							"lerp_mode": "catmullrom"
						},
						"1.25": {
							"post": {
								"vector": [0, 0, 0]
							},
							"lerp_mode": "catmullrom"
						},
						"1.5": {
							"post": {
								"vector": [15, 0, 0]
							},
							"lerp_mode": "catmullrom"
						},
						"1.75": {
							"post": {
								"vector": [0, 0, 0]
							},
							"lerp_mode": "catmullrom"
						},
						"2.0": {
							"post": {
								"vector": [15, 0, 0]
							},
							"lerp_mode": "catmullrom"
						},
						"2.25": {
							"vector": [0, 0, 0]
						},
						"2.75": {
							"vector": [0, 0, 0]
						}
					},
					"position": {
						"0.0": {
							"vector": [0, 0, 0]
						},
						"0.2083": {
							"vector": [0, 0, 0]
						},
						"0.75": {
							"vector": [0, 0, 0]
						},
						"1.25": {
							"vector": [0, 0, 0]
						},
						"1.75": {
							"vector": [0, 0, 0]
						},
						"2.25": {
							"vector": [0, 0, 0]
						},
						"2.75": {
							"vector": [0, 0, 0]
						}
					}
				},
				"Arm": {
					"rotation": {
						"0.0": {
							"post": {
								"vector": [0, 0, 0]
							},
							"lerp_mode": "catmullrom"
						},
						"0.7917": {
							"post": {
								"vector": [-50, 0, -17.5]
							},
							"lerp_mode": "catmullrom"
						},
						"2.375": {
							"post": {
								"vector": [-50, 0, -17.5]
							},
							"lerp_mode": "catmullrom"
						},
						"2.75": {
							"post": {
								"vector": [0, 0, 0]
							},
							"lerp_mode": "catmullrom"
						}
					},
					"position": {
						"0.0": {
							"post": {
								"vector": [0, 0, 0]
							},
							"lerp_mode": "catmullrom"
						},
						"2.75": {
							"post": {
								"vector": [0, 0, 0]
							},
							"lerp_mode": "catmullrom"
						}
					}
				},
				"Arm2": {
					"rotation": {
						"0.0": {
							"post": {
								"vector": [0, 0, 0]
							},
							"lerp_mode": "catmullrom"
						},
						"0.7917": {
							"post": {
								"vector": [-50, 0, 17.5]
							},
							"lerp_mode": "catmullrom"
						},
						"2.375": {
							"post": {
								"vector": [-50, 0, 17.5]
							},
							"lerp_mode": "catmullrom"
						},
						"2.75": {
							"post": {
								"vector": [0, 0, 0]
							},
							"lerp_mode": "catmullrom"
						}
					},
					"position": {
						"0.0": {
							"post": {
								"vector": [0, 0, 0]
							},
							"lerp_mode": "catmullrom"
						},
						"2.75": {
							"post": {
								"vector": [0, 0, 0]
							},
							"lerp_mode": "catmullrom"
						}
					}
				}
			}
		}
	}
}